ccs/__init__.py
ccs/ccs_anat_01_pre_freesurfer.py
ccs/ccs_anat_02_freesurfer.py
ccs/ccs_anat_03_postfs.py
ccs/say_hello.py
ccs/utils/__init__.py
ccs/utils/run_command.py
ccspy/__init__.py
ccspy/ccs_anat.py
ccspy/ccs_anat_01_pre_freesurfer.py
ccspy/ccs_anat_02_freesurfer.py
ccspy/ccs_anat_03_postfs.py
ccspy/ccspy_anat.py
ccspy/ccspy_anat_01_pre_freesurfer.py
ccspy/ccspy_anat_02_freesurfer.py
ccspy/ccspy_anat_03_postfs.py
ccspy/errors.log
ccspy/info.log
ccspy/say_hello
ccspy/say_hello.py
ccspy/__pycache__/__init__.cpython-36.pyc
ccspy/__pycache__/ccspy_anat_01_pre_freesurfer.cpython-36.pyc
ccspy/__pycache__/ccspy_anat_02_freesurfer.cpython-36.pyc
ccspy/__pycache__/ccspy_anat_03_postfs.cpython-36.pyc
ccspy/__pycache__/say_hello.cpython-36.pyc
ccspy/utils/__init__.py
ccspy/utils/file_util.py
ccspy/utils/logging_config.json
ccspy/utils/logging_config_util.py
ccspy/utils/run_command.py
ccspy/utils/run_command_util.py
ccspy/utils/__pycache__/__init__.cpython-36.pyc
ccspy/utils/__pycache__/file_util.cpython-36.pyc
ccspy/utils/__pycache__/logging_config_util.cpython-36.pyc
ccspy/utils/__pycache__/run_command_util.cpython-36.pyc
ccspy-0.0.16.data/data/README.md
ccspy-0.0.16.dist-info/METADATA
ccspy-0.0.16.dist-info/WHEEL
ccspy-0.0.16.dist-info/entry_points.txt
ccspy-0.0.16.dist-info/top_level.txt
ccspy-0.0.16.dist-info/RECORD
