Metadata-Version: 2.1
Name: ccspy
Version: 0.0.16
Summary: A CCS PACKAGE
Home-page: UNKNOWN
Author: dzjin
Author-email: dzjin5678@163.com
License: UNKNOWN
Platform: UNKNOWN
Classifier: Programming Language :: Python :: 3
Classifier: License :: OSI Approved :: MIT License
Classifier: Operating System :: POSIX :: Linux
Requires-Python: >=3.0
Requires-Dist: docopt
Requires-Dist: antspyx
